py3data/__init__.py
py3data/_version.py
py3data/api.py
py3data/xmltodict.py
py3data-0.3.2.dist-info/LICENSE
py3data-0.3.2.dist-info/METADATA
py3data-0.3.2.dist-info/WHEEL
py3data-0.3.2.dist-info/top_level.txt
py3data-0.3.2.dist-info/RECORD
